silverback/__init__.py
silverback/_build_utils.py
silverback/_cli.py
silverback/_click_ext.py
silverback/_importer.py
silverback/exceptions.py
silverback/main.py
silverback/middlewares.py
silverback/py.typed
silverback/recorder.py
silverback/runner.py
silverback/settings.py
silverback/state.py
silverback/types.py
silverback/utils.py
silverback/version.py
silverback/worker.py
silverback/cluster/__init__.py
silverback/cluster/auth.py
silverback/cluster/client.py
silverback/cluster/mcp.py
silverback/cluster/settings.py
silverback/cluster/types.py
silverback/cluster/utils.py
silverback-0.7.38.dist-info/licenses/LICENSE
silverback-0.7.38.dist-info/METADATA
silverback-0.7.38.dist-info/WHEEL
silverback-0.7.38.dist-info/entry_points.txt
silverback-0.7.38.dist-info/top_level.txt
silverback-0.7.38.dist-info/RECORD
