Metadata-Version: 2.4
Name: silverback
Version: 0.7.38
Summary: Listen and respond to on-chain events in real-time
Author-email: "ApeWorX Ltd." <admin@apeworx.io>
License-Expression: Apache-2.0
Project-URL: Homepage, https://silverback.apeworx.io
Project-URL: Repository, https://github.com/ApeWorX/silverback.git
Project-URL: Issues, https://github.com/ApeWorX/silverback/issues
Project-URL: Documentation, https://docs.apeworx.io/silverback
Project-URL: Funding, https://github.com/sponsors/ApeWorX
Project-URL: Twitter / X, https://x.com/ApeFramework
Keywords: silverback,bots,crypto,ethereum,automation,defi
Classifier: Development Status :: 5 - Production/Stable
Classifier: Intended Audience :: Developers
Classifier: Natural Language :: English
Classifier: Operating System :: MacOS
Classifier: Operating System :: POSIX
Classifier: Programming Language :: Python :: 3
Classifier: Programming Language :: Python :: 3.10
Classifier: Programming Language :: Python :: 3.11
Classifier: Programming Language :: Python :: 3.12
Classifier: Programming Language :: Python :: 3.13
Requires-Python: <4,>=3.10
License-File: LICENSE
Requires-Dist: apepay<1,>=0.3.5
Requires-Dist: click
Requires-Dist: eth-ape<1,>=0.8.38
Requires-Dist: ethpm-types>=0.6.10
Requires-Dist: eth-pydantic-types
Requires-Dist: exceptiongroup; python_version < "3.11"
Requires-Dist: httpx<1,>=0.28
Requires-Dist: jwcrypto<2,>=1.4
Requires-Dist: packaging
Requires-Dist: pycron<4,>=3.1
Requires-Dist: pydantic_settings
Requires-Dist: python-dotenv<2,>=1.1.1
Requires-Dist: quattro<26,>=25.2
Requires-Dist: taskiq[metrics]<0.13,>=0.12.1
Requires-Dist: tomlkit<1,>=0.12
Requires-Dist: yaspin<4,>=3.1
Provides-Extra: mcp
Requires-Dist: fastmcp; extra == "mcp"
Provides-Extra: build
Requires-Dist: taskiq-aio-pika<1,>=0.5; extra == "build"
Requires-Dist: taskiq-redis<2,>=1.2; extra == "build"
Provides-Extra: recommended-plugins
Requires-Dist: ape-arbitrum; extra == "recommended-plugins"
Requires-Dist: ape-avalanche; extra == "recommended-plugins"
Requires-Dist: ape-base; extra == "recommended-plugins"
Requires-Dist: ape-bsc; extra == "recommended-plugins"
Requires-Dist: ape-optimism; extra == "recommended-plugins"
Requires-Dist: ape-polygon; extra == "recommended-plugins"
Requires-Dist: ape-sonic; extra == "recommended-plugins"
Requires-Dist: ape-etherscan; extra == "recommended-plugins"
Requires-Dist: ape-ens; extra == "recommended-plugins"
Requires-Dist: ape-tokens; extra == "recommended-plugins"
Requires-Dist: ape-alchemy; extra == "recommended-plugins"
Requires-Dist: ape-infura; extra == "recommended-plugins"
Requires-Dist: ape-drpc; extra == "recommended-plugins"
Requires-Dist: ape-erpc; extra == "recommended-plugins"
Requires-Dist: ape-aws; extra == "recommended-plugins"
Dynamic: license-file
